flake8_assign_and_return.py
flake8_assign_and_return-0.0.4.dist-info/METADATA
flake8_assign_and_return-0.0.4.dist-info/WHEEL
flake8_assign_and_return-0.0.4.dist-info/entry_points.txt
flake8_assign_and_return-0.0.4.dist-info/top_level.txt
flake8_assign_and_return-0.0.4.dist-info/RECORD
