Metadata-Version: 2.1
Name: flake8-assign-and-return
Version: 0.0.4
Summary: A flake8 extension that checks for assignment and return in Python
Home-page: https://github.com/sbdchd/flake8-assign-and-return
Author: Steve Dignam
Author-email: steve@dignam.xyz
Maintainer: Steve Dignam
Maintainer-email: steve@dignam.xyz
License: BSD2 License
Keywords: flake8,lint
Platform: UNKNOWN
Classifier: Intended Audience :: Developers
Classifier: Environment :: Console
Classifier: Programming Language :: Python :: 3.6
Classifier: Operating System :: OS Independent
Classifier: License :: OSI Approved :: MIT License
Classifier: Topic :: Software Development :: Quality Assurance
Provides: flake8_assign_and_return
Requires-Dist: flake8
